py_dic/__init__.py
py_dic/__main__.py
py_dic/dic.py
py_dic/dic_tools.py
py_dic/main.py
py_dic/settings.ini
py_dic-0.1.1.dist-info/METADATA
py_dic-0.1.1.dist-info/WHEEL
py_dic-0.1.1.dist-info/top_level.txt
py_dic-0.1.1.dist-info/RECORD
