Metadata-Version: 2.1
Name: py-dic
Version: 0.1.1
Summary: A DIgital Image Correlation implementation in Python using the SciPy stack.
Home-page: https://github.com/ladisk/pyDIC
Author: Domen Gorjup
Author-email: domen_gorjup@hotmail.com
License: UNKNOWN
Keywords: computer vision dic
Platform: UNKNOWN
Classifier: Development Status :: 3 - Alpha
Classifier: Intended Audience :: Developers
Classifier: Topic :: Scientific/Engineering
Classifier: Programming Language :: Python :: 3.6
Requires-Dist: cycler (>=0.10.0)
Requires-Dist: kiwisolver (>=1.0.1)
Requires-Dist: matplotlib (>=2.2.2)
Requires-Dist: numpy (>=1.14.0)
Requires-Dist: pyparsing (==2.2.0)
Requires-Dist: PyQt5 (>=5.10.1)
Requires-Dist: pyqtgraph (>=0.10.0)
Requires-Dist: python-dateutil (==2.7.2)
Requires-Dist: pytz (==2018.3)
Requires-Dist: scipy (>=1.0.1)
Requires-Dist: sip (==4.19.8)
Requires-Dist: six (==1.11.0)
Requires-Dist: tqdm (>=4.20.0)
